pyscbwrapper/__init__.py
pyscbwrapper/scb.py
pyscbwrapper-0.1.2.dist-info/licenses/LICENSE
pyscbwrapper-0.1.2.dist-info/METADATA
pyscbwrapper-0.1.2.dist-info/WHEEL
pyscbwrapper-0.1.2.dist-info/top_level.txt
pyscbwrapper-0.1.2.dist-info/RECORD
