Metadata-Version: 2.4
Name: pyscbwrapper
Version: 0.1.2
Summary: Python wrapper for Statistics Sweden's API, which can be found at https://www.scb.se/en/api.
Home-page: https://github.com/kirajcg/pyscbwrapper
Author: Kira Coder Gylling
Author-email: kira.gylling@gmail.com
License: MIT
Classifier: License :: OSI Approved :: MIT License
Classifier: Operating System :: OS Independent
License-File: LICENSE
Requires-Dist: requests>=2.21.0
Dynamic: author
Dynamic: author-email
Dynamic: classifier
Dynamic: description
Dynamic: description-content-type
Dynamic: home-page
Dynamic: license
Dynamic: license-file
Dynamic: requires-dist
Dynamic: summary
